pyspark_udtf/__init__.py
pyspark_udtf/udtfs/__init__.py
pyspark_udtf/udtfs/fuzzy_match.py
pyspark_udtf/udtfs/image_caption.py
pyspark_udtf/udtfs/mapping_engine.py
pyspark_udtf/udtfs/meta_capi.py
pyspark_udtf/utils/__init__.py
pyspark_udtf/utils/version_check.py
pyspark_udtf-0.1.1.dist-info/METADATA
pyspark_udtf-0.1.1.dist-info/WHEEL
pyspark_udtf-0.1.1.dist-info/RECORD
