Metadata-Version: 2.4
Name: pyspark-udtf
Version: 0.1.1
Summary: A collection of PySpark User-Defined Table Functions (UDTFs)
Project-URL: Repository, https://github.com/allisonwang-db/pyspark-udtf
Project-URL: Issues, https://github.com/allisonwang-db/pyspark-udtf/issues
Author-email: Allison Wang <allisowang@apache.org>
License: Apache-2.0
Classifier: Development Status :: 3 - Alpha
Classifier: Intended Audience :: Developers
Classifier: Programming Language :: Python :: 3
Classifier: Programming Language :: Python :: 3.10
Classifier: Programming Language :: Python :: 3.11
Classifier: Programming Language :: Python :: 3.12
Requires-Python: >=3.10
Requires-Dist: pandas
Requires-Dist: pyarrow
Requires-Dist: pyspark>=4.0.0
Requires-Dist: pyyaml
Requires-Dist: requests
Provides-Extra: dev
Requires-Dist: pytest; extra == 'dev'
Requires-Dist: pytest-mock; extra == 'dev'
